pandas_save_profiler/__init__.py
pandas_save_profiler/_humanize.py
pandas_save_profiler/extractors.py
pandas_save_profiler/save_profiler.py
pandas_save_profiler-0.0.0.dist-info/LICENSE
pandas_save_profiler-0.0.0.dist-info/METADATA
pandas_save_profiler-0.0.0.dist-info/WHEEL
pandas_save_profiler-0.0.0.dist-info/top_level.txt
pandas_save_profiler-0.0.0.dist-info/RECORD
