Metadata-Version: 2.1
Name: pandas-save-profiler
Version: 0.0.0
Summary: Tools to evaluate pandas performance when saving dataframes in different file formats.
Home-page: https://github.com/dmontaner/pandas_save_profiler
Author: David Montaner
Author-email: david.montaner@gmail.com
License: MIT
Project-URL: Source Code, https://github.com/dmontaner/pandas_save_profiler
Project-URL: Documentation, https://github.com/dmontaner/pandas_save_profiler
Project-URL: Issue Tracker, https://github.com/dmontaner/pandas_save_profiler/issues
Keywords: pandas,save,profile
Platform: UNKNOWN
Classifier: Development Status :: 3 - Alpha
Classifier: Intended Audience :: Developers
Classifier: License :: OSI Approved :: MIT License
Classifier: Operating System :: Unix
Classifier: Operating System :: POSIX
Classifier: Operating System :: MacOS
Classifier: Operating System :: Microsoft :: Windows
Classifier: Programming Language :: Python
Classifier: Programming Language :: Python :: 3
Classifier: Programming Language :: Python :: 3.6
Classifier: Programming Language :: Python :: 3.7
Classifier: Programming Language :: Python :: 3.8
Classifier: Programming Language :: Python :: Implementation :: CPython
Classifier: Programming Language :: Python :: Implementation :: PyPy
Classifier: Topic :: Utilities
Classifier: Topic :: Scientific/Engineering
Classifier: Intended Audience :: Developers
Classifier: Intended Audience :: Science/Research
Requires-Python: >=3.6
Requires-Dist: pandas
Requires-Dist: humanize
Requires-Dist: memory-profiler (>=0.57.0)
Requires-Dist: pyarrow
Requires-Dist: SQLAlchemy
Requires-Dist: xlwt
Requires-Dist: xlrd
Requires-Dist: openpyxl
